[{"id":0,"originalId":"00ae3bca-1dc4-41ce-ac2e-8a1823697688","duration":3,"deadline":119,"compatibleMachines":["3","4","5","6","10","11","13"],"compatibleCages":[1],"compatibleCouvettes":[2,3],"machineSetup":{"height":0,"shape":0,"cage":1,"couvette":3,"remeltingMachine":false}},{"id":1,"originalId":"05764685-fe16-495c-9154-ae63ce252358","duration":2,"deadline":158,"compatibleMachines":["3","4","5","6","10","11","12","13"],"compatibleCages":[1],"compatibleCouvettes":[3],"machineSetup":{"height":0,"shape":1,"cage":1,"couvette":3,"remeltingMachine":false}},{"id":2,"originalId":"06e5655d-e6fe-4f6c-a26a-b1e27870c8a9","duration":18,"deadline":31,"compatibleMachines":["3","4","5","6","10","11","13"],"compatibleCages":[1],"compatibleCouvettes":[3],"machineSetup":{"height":1,"shape":0,"cage":1,"couvette":3,"remeltingMachine":false}},{"id":3,"originalId":"06e5655d-e6fe-4f6c-a26a-b1e27870c8a9","duration":18,"deadline":31,"compatibleMachines":["3","4","5","6","10","11","13"],"compatibleCages":[1],"compatibleCouvettes":[3],"machineSetup":{"height":1,"shape":0,"cage":1,"couvette":3,"remeltingMachine":false}},{"id":4,"originalId":"06e5655d-e6fe-4f6c-a26a-b1e27870c8a9","duration":18,"deadline":31,"compatibleMachines":["3","4","5","6","10","11","13"],"compatibleCages":[1],"compatibleCouvettes":[3],"machineSetup":{"height":1,"shape":0,"cage":1,"couvette":3,"remeltingMachine":false}},{"id":5,"originalId":"06e5655d-e6fe-4f6c-a26a-b1e27870c8a9","duration":18,"deadline":31,"compatibleMachines":["3","4","5","6","10","11","13"],"compatibleCages":[1],"compatibleCouvettes":[3],"machineSetup":{"height":1,"shape":0,"cage":1,"couvette":3,"remeltingMachine":false}},{"id":6,"originalId":"06e5655d-e6fe-4f6c-a26a-b1e27870c8a9","duration":18,"deadline":31,"compatibleMachines":["3","4","5","6","10","11","13"],"compatibleCages":[1],"compatibleCouvettes":[3],"machineSetup":{"height":1,"shape":0,"cage":1,"couvette":3,"remeltingMachine":false}},{"id":7,"originalId":"06e5655d-e6fe-4f6c-a26a-b1e27870c8a9","duration":18,"deadline":31,"compatibleMachines":["3","4","5","6","10","11","13"],"compatibleCages":[1],"compatibleCouvettes":[3],"machineSetup":{"height":1,"shape":0,"cage":1,"couvette":3,"remeltingMachine":false}},{"id":8,"originalId":"06e5655d-e6fe-4f6c-a26a-b1e27870c8a9","duration":17,"deadline":31,"compatibleMachines":["3","4","5","6","10","11","13"],"compatibleCages":[1],"compatibleCouvettes":[3],"machineSetup":{"height":1,"shape":0,"cage":1,"couvette":3,"remeltingMachine":false}},{"id":9,"originalId":"07deaafb-66d7-4fa7-a627-377996e17067","duration":18,"deadline":63,"compatibleMachines":["3","4","5","6","10","11","13"],"compatibleCages":[1],"compatibleCouvettes":[2,3],"machineSetup":{"height":0,"shape":1,"cage":1,"couvette":3,"remeltingMachine":false}},{"id":10,"originalId":"07deaafb-66d7-4fa7-a627-377996e17067","duration":18,"deadline":63,"compatibleMachines":["3","4","5","6","10","11","13"],"compatibleCages":[1],"compatibleCouvettes":[2,3],"machineSetup":{"height":0,"shape":1,"cage":1,"couvette":3,"remeltingMachine":false}},{"id":11,"originalId":"07deaafb-66d7-4fa7-a627-377996e17067","duration":5,"deadline":63,"compatibleMachines":["3","4","5","6","10","11","13"],"compatibleCages":[1],"compatibleCouvettes":[2,3],"machineSetup":{"height":0,"shape":1,"cage":1,"couvette":3,"remeltingMachine":false}},{"id":12,"originalId":"0f39e0bb-7d7e-4999-a06b-6f8510dd9c7e","duration":2,"deadline":-79,"compatibleMachines":["3","4","5","6","10","11","13"],"compatibleCages":[1],"compatibleCouvettes":[0],"machineSetup":{"height":0,"shape":1,"cage":1,"couvette":0,"remeltingMachine":false}},{"id":13,"originalId":"113ff47a-893e-475a-a35a-3101e6f91573","duration":16,"deadline":130,"compatibleMachines":["3","4","5","6","10","11","13"],"compatibleCages":[1,0],"compatibleCouvettes":[2],"machineSetup":{"height":1,"shape":1,"cage":1,"couvette":2,"remeltingMachine":false}},{"id":14,"originalId":"12444387-8e84-4c17-a47c-fa6ac009af23","duration":3,"deadline":23,"compatibleMachines":["3","4","5","6","10","11","12","13"],"compatibleCages":[1,0],"compatibleCouvettes":[2,3],"machineSetup":{"height":1,"shape":1,"cage":1,"couvette":3,"remeltingMachine":false}},{"id":15,"originalId":"13b3fff9-7d58-4206-8c0d-32e04ec1e227","duration":2,"deadline":158,"compatibleMachines":["3","4","5","6","10","11","13"],"compatibleCages":[1,0],"compatibleCouvettes":[2],"machineSetup":{"height":1,"shape":1,"cage":1,"couvette":2,"remeltingMachine":false}},{"id":16,"originalId":"1e5ccf42-a7e0-4f9b-9708-f8308dfce917","duration":2,"deadline":158,"compatibleMachines":["3","4","5","6","10","11","13"],"compatibleCages":[1,0],"compatibleCouvettes":[2,3],"machineSetup":{"height":1,"shape":1,"cage":1,"couvette":3,"remeltingMachine":false}},{"id":17,"originalId":"1fcaf12c-2022-43c5-884f-ffa11a183228","duration":18,"deadline":1,"compatibleMachines":["4","11"],"compatibleCages":[1],"compatibleCouvettes":[5],"machineSetup":{"height":1,"shape":1,"cage":1,"couvette":5,"remeltingMachine":false}},{"id":18,"originalId":"1fcaf12c-2022-43c5-884f-ffa11a183228","duration":2,"deadline":1,"compatibleMachines":["4","11"],"compatibleCages":[1],"compatibleCouvettes":[5],"machineSetup":{"height":1,"shape":1,"cage":1,"couvette":5,"remeltingMachine":false}},{"id":19,"originalId":"283f9318-d4ff-4abf-8694-979a1f605915","duration":18,"deadline":223,"compatibleMachines":["3","4","5","6","10","11","13"],"compatibleCages":[1,0],"compatibleCouvettes":[3],"machineSetup":{"height":1,"shape":1,"cage":1,"couvette":3,"remeltingMachine":false}},{"id":20,"originalId":"2a592633-c341-40f6-aee0-29ea29151439","duration":3,"deadline":-13,"compatibleMachines":["3","4","5","6","10","11","13"],"compatibleCages":[1,0],"compatibleCouvettes":[1,2],"machineSetup":{"height":1,"shape":1,"cage":1,"couvette":2,"remeltingMachine":false}},{"id":21,"originalId":"2c3b519d-23de-46b9-b08a-cb260f3817c8","duration":2,"deadline":7,"compatibleMachines":["3","4","5","6","10","11","13"],"compatibleCages":[1,0],"compatibleCouvettes":[3],"machineSetup":{"height":1,"shape":0,"cage":1,"couvette":3,"remeltingMachine":false}},{"id":22,"originalId":"321c866b-bc26-43ef-8bd1-89bb26c1f467","duration":4,"deadline":131,"compatibleMachines":["3","4","5","6","10","11","13"],"compatibleCages":[1,0],"compatibleCouvettes":[3],"machineSetup":{"height":1,"shape":1,"cage":1,"couvette":3,"remeltingMachine":false}},{"id":23,"originalId":"393cc0e7-50f8-4b7f-b941-f11eb0a029ff","duration":3,"deadline":189,"compatibleMachines":["3","4","5","6","10","11","13"],"compatibleCages":[1],"compatibleCouvettes":[3],"machineSetup":{"height":1,"shape":1,"cage":1,"couvette":3,"remeltingMachine":false}},{"id":24,"originalId":"3ce7a6f8-74c6-4e74-a074-c66e18ed8db0","duration":18,"deadline":158,"compatibleMachines":["3","4","5","6","10","11","13"],"compatibleCages":[1,0],"compatibleCouvettes":[2,3],"machineSetup":{"height":1,"shape":1,"cage":1,"couvette":3,"remeltingMachine":false}},{"id":25,"originalId":"3ce7a6f8-74c6-4e74-a074-c66e18ed8db0","duration":18,"deadline":158,"compatibleMachines":["3","4","5","6","10","11","13"],"compatibleCages":[1,0],"compatibleCouvettes":[2,3],"machineSetup":{"height":1,"shape":1,"cage":1,"couvette":3,"remeltingMachine":false}},{"id":26,"originalId":"3ce7a6f8-74c6-4e74-a074-c66e18ed8db0","duration":4,"deadline":158,"compatibleMachines":["3","4","5","6","10","11","13"],"compatibleCages":[1,0],"compatibleCouvettes":[2,3],"machineSetup":{"height":1,"shape":1,"cage":1,"couvette":3,"remeltingMachine":false}},{"id":27,"originalId":"42fa825b-54d2-4e47-a314-1fd97123cbe3","duration":18,"deadline":7,"compatibleMachines":["3","4","5","6","10","11","13"],"compatibleCages":[1,0],"compatibleCouvettes":[2,3],"machineSetup":{"height":1,"shape":1,"cage":1,"couvette":3,"remeltingMachine":false}},{"id":28,"originalId":"42fa825b-54d2-4e47-a314-1fd97123cbe3","duration":18,"deadline":7,"compatibleMachines":["3","4","5","6","10","11","13"],"compatibleCages":[1,0],"compatibleCouvettes":[2,3],"machineSetup":{"height":1,"shape":1,"cage":1,"couvette":3,"remeltingMachine":false}},{"id":29,"originalId":"42fa825b-54d2-4e47-a314-1fd97123cbe3","duration":17,"deadline":7,"compatibleMachines":["3","4","5","6","10","11","13"],"compatibleCages":[1,0],"compatibleCouvettes":[2,3],"machineSetup":{"height":1,"shape":1,"cage":1,"couvette":3,"remeltingMachine":false}},{"id":30,"originalId":"44a582e3-a053-49c5-a414-cc955ab72df9","duration":3,"deadline":129,"compatibleMachines":["3","4","5","6","10","11","13"],"compatibleCages":[1,0],"compatibleCouvettes":[2],"machineSetup":{"height":1,"shape":1,"cage":1,"couvette":2,"remeltingMachine":false}},{"id":31,"originalId":"4883613e-5691-493f-bb4b-eea37f316bd2","duration":4,"deadline":115,"compatibleMachines":["3","4","5","6","10","11","13"],"compatibleCages":[1,0],"compatibleCouvettes":[2,3],"machineSetup":{"height":1,"shape":1,"cage":1,"couvette":3,"remeltingMachine":false}},{"id":32,"originalId":"488dd2be-639e-4e65-9850-a9589fef731a","duration":18,"deadline":43,"compatibleMachines":["3","4","5","6","10","11","13"],"compatibleCages":[1,0],"compatibleCouvettes":[3],"machineSetup":{"height":1,"shape":1,"cage":1,"couvette":3,"remeltingMachine":false}},{"id":33,"originalId":"488dd2be-639e-4e65-9850-a9589fef731a","duration":18,"deadline":43,"compatibleMachines":["3","4","5","6","10","11","13"],"compatibleCages":[1,0],"compatibleCouvettes":[3],"machineSetup":{"height":1,"shape":1,"cage":1,"couvette":3,"remeltingMachine":false}},{"id":34,"originalId":"488dd2be-639e-4e65-9850-a9589fef731a","duration":18,"deadline":43,"compatibleMachines":["3","4","5","6","10","11","13"],"compatibleCages":[1,0],"compatibleCouvettes":[3],"machineSetup":{"height":1,"shape":1,"cage":1,"couvette":3,"remeltingMachine":false}},{"id":35,"originalId":"488dd2be-639e-4e65-9850-a9589fef731a","duration":18,"deadline":43,"compatibleMachines":["3","4","5","6","10","11","13"],"compatibleCages":[1,0],"compatibleCouvettes":[3],"machineSetup":{"height":1,"shape":1,"cage":1,"couvette":3,"remeltingMachine":false}},{"id":36,"originalId":"488dd2be-639e-4e65-9850-a9589fef731a","duration":18,"deadline":43,"compatibleMachines":["3","4","5","6","10","11","13"],"compatibleCages":[1,0],"compatibleCouvettes":[3],"machineSetup":{"height":1,"shape":1,"cage":1,"couvette":3,"remeltingMachine":false}},{"id":37,"originalId":"488dd2be-639e-4e65-9850-a9589fef731a","duration":2,"deadline":43,"compatibleMachines":["3","4","5","6","10","11","13"],"compatibleCages":[1,0],"compatibleCouvettes":[3],"machineSetup":{"height":1,"shape":1,"cage":1,"couvette":3,"remeltingMachine":false}},{"id":38,"originalId":"4914e18c-c5f7-4e9e-9a43-c05260a9b333","duration":2,"deadline":158,"compatibleMachines":["3","4","5","6","10","11","13"],"compatibleCages":[1],"compatibleCouvettes":[3],"machineSetup":{"height":0,"shape":0,"cage":1,"couvette":3,"remeltingMachine":false}},{"id":39,"originalId":"4c97ebb5-ee4b-4499-af6e-ab595e9b6fb9","duration":7,"deadline":79,"compatibleMachines":["3","4","5","6","10","11","12","13"],"compatibleCages":[0],"compatibleCouvettes":[2],"machineSetup":{"height":1,"shape":1,"cage":0,"couvette":2,"remeltingMachine":false}},{"id":40,"originalId":"4d0a517f-d951-4f47-84a1-e88bd6a07dd0","duration":2,"deadline":158,"compatibleMachines":["3","4","5","6","10","11","13"],"compatibleCages":[1,0],"compatibleCouvettes":[3],"machineSetup":{"height":1,"shape":1,"cage":1,"couvette":3,"remeltingMachine":false}},{"id":41,"originalId":"4d55ca8e-5ed1-48ff-bde4-d0803a698f04","duration":9,"deadline":131,"compatibleMachines":["3","4","5","6","10","11","13"],"compatibleCages":[1,0],"compatibleCouvettes":[2,3],"machineSetup":{"height":1,"shape":1,"cage":1,"couvette":3,"remeltingMachine":false}},{"id":42,"originalId":"4e5fdb36-800c-483b-bf6c-892e2eec7e82","duration":2,"deadline":189,"compatibleMachines":["3","4","5","6","10","11","13"],"compatibleCages":[1],"compatibleCouvettes":[2,3],"machineSetup":{"height":0,"shape":0,"cage":1,"couvette":3,"remeltingMachine":false}},{"id":43,"originalId":"4f17e338-5728-478b-9824-844b19772b41","duration":2,"deadline":158,"compatibleMachines":["3","4","5","6","10","11","12","13"],"compatibleCages":[1,0],"compatibleCouvettes":[3],"machineSetup":{"height":1,"shape":1,"cage":1,"couvette":3,"remeltingMachine":false}},{"id":44,"originalId":"51a404d4-4fb6-4e9a-bdee-95ce0fdb860d","duration":4,"deadline":-8,"compatibleMachines":["3","4","5","6","10","11","12","13"],"compatibleCages":[1,0],"compatibleCouvettes":[2,3],"machineSetup":{"height":1,"shape":1,"cage":1,"couvette":3,"remeltingMachine":false}},{"id":45,"originalId":"52e17a05-8f23-4305-9056-61ddd3da2047","duration":4,"deadline":-13,"compatibleMachines":["4","11"],"compatibleCages":[1],"compatibleCouvettes":[5],"machineSetup":{"height":1,"shape":1,"cage":1,"couvette":5,"remeltingMachine":false}},{"id":46,"originalId":"5762e425-3ee7-49e7-9a65-81a10227a229","duration":5,"deadline":189,"compatibleMachines":["4","11"],"compatibleCages":[1,0],"compatibleCouvettes":[3],"machineSetup":{"height":1,"shape":1,"cage":1,"couvette":3,"remeltingMachine":false}},{"id":47,"originalId":"5ac7e15c-9990-4514-b118-0625eb9e7095","duration":2,"deadline":189,"compatibleMachines":["3","4","5","6","10","11","13"],"compatibleCages":[1,0],"compatibleCouvettes":[1],"machineSetup":{"height":0,"shape":1,"cage":1,"couvette":1,"remeltingMachine":false}},{"id":48,"originalId":"6764712c-e50d-4001-ae2f-0c3cfed1a374","duration":4,"deadline":-13,"compatibleMachines":["3","4","5","6","10","11","13"],"compatibleCages":[1,0],"compatibleCouvettes":[2,3],"machineSetup":{"height":1,"shape":1,"cage":1,"couvette":3,"remeltingMachine":false}},{"id":49,"originalId":"6ca0b984-4bec-402f-8c13-f8c768c31609","duration":18,"deadline":101,"compatibleMachines":["3","4","5","6","10","11","13"],"compatibleCages":[1,0],"compatibleCouvettes":[2,3],"machineSetup":{"height":1,"shape":1,"cage":1,"couvette":3,"remeltingMachine":false}},{"id":50,"originalId":"6fb99b12-a712-4dc7-bbb2-5942f2491a42","duration":9,"deadline":74,"compatibleMachines":["3","4","5","6","10","11","13"],"compatibleCages":[1,0],"compatibleCouvettes":[1],"machineSetup":{"height":1,"shape":0,"cage":1,"couvette":1,"remeltingMachine":false}},{"id":51,"originalId":"72a2f29d-0971-453a-b90d-c4ff92183db3","duration":18,"deadline":42,"compatibleMachines":["3","4","5","6","10","11","13"],"compatibleCages":[1],"compatibleCouvettes":[3],"machineSetup":{"height":0,"shape":1,"cage":1,"couvette":3,"remeltingMachine":false}},{"id":52,"originalId":"72a2f29d-0971-453a-b90d-c4ff92183db3","duration":4,"deadline":42,"compatibleMachines":["3","4","5","6","10","11","13"],"compatibleCages":[1],"compatibleCouvettes":[3],"machineSetup":{"height":0,"shape":1,"cage":1,"couvette":3,"remeltingMachine":false}},{"id":53,"originalId":"72fd92ba-9b32-458c-8f65-4f35ce12d95a","duration":2,"deadline":145,"compatibleMachines":["3","4","5","6","10","11","12","13"],"compatibleCages":[1,0],"compatibleCouvettes":[1],"machineSetup":{"height":1,"shape":1,"cage":1,"couvette":1,"remeltingMachine":false}},{"id":54,"originalId":"7443be2f-4a41-437e-8666-53d4bbcac49b","duration":18,"deadline":11,"compatibleMachines":["3","4","5","6","10","11","13"],"compatibleCages":[1,0],"compatibleCouvettes":[2,3],"machineSetup":{"height":1,"shape":1,"cage":1,"couvette":3,"remeltingMachine":false}},{"id":55,"originalId":"7443be2f-4a41-437e-8666-53d4bbcac49b","duration":3,"deadline":11,"compatibleMachines":["3","4","5","6","10","11","13"],"compatibleCages":[1,0],"compatibleCouvettes":[2,3],"machineSetup":{"height":1,"shape":1,"cage":1,"couvette":3,"remeltingMachine":false}},{"id":56,"originalId":"74c1c0a9-3b93-440b-b0d0-467a1ec40d34","duration":18,"deadline":-18,"compatibleMachines":["3","4","5","6","10","11","13"],"compatibleCages":[1,0],"compatibleCouvettes":[1,2],"machineSetup":{"height":1,"shape":1,"cage":1,"couvette":2,"remeltingMachine":false}},{"id":57,"originalId":"74c1c0a9-3b93-440b-b0d0-467a1ec40d34","duration":18,"deadline":-18,"compatibleMachines":["3","4","5","6","10","11","13"],"compatibleCages":[1,0],"compatibleCouvettes":[1,2],"machineSetup":{"height":1,"shape":1,"cage":1,"couvette":2,"remeltingMachine":false}},{"id":58,"originalId":"74c1c0a9-3b93-440b-b0d0-467a1ec40d34","duration":2,"deadline":-18,"compatibleMachines":["3","4","5","6","10","11","13"],"compatibleCages":[1,0],"compatibleCouvettes":[1,2],"machineSetup":{"height":1,"shape":1,"cage":1,"couvette":2,"remeltingMachine":false}},{"id":59,"originalId":"77820451-7e77-45d8-8518-809e618c3be2","duration":2,"deadline":80,"compatibleMachines":["4","11"],"compatibleCages":[1],"compatibleCouvettes":[5],"machineSetup":{"height":0,"shape":1,"cage":1,"couvette":5,"remeltingMachine":false}},{"id":60,"originalId":"78c641fa-31b4-4146-a944-1789b75168a5","duration":4,"deadline":189,"compatibleMachines":["3","4","5","6","10","11","13"],"compatibleCages":[1,0],"compatibleCouvettes":[2],"machineSetup":{"height":0,"shape":1,"cage":1,"couvette":2,"remeltingMachine":false}},{"id":61,"originalId":"7a9a8ae8-4cf5-437e-aac3-fd9a31d10101","duration":2,"deadline":-581,"compatibleMachines":["3","6"],"compatibleCages":[1],"compatibleCouvettes":[1,2],"machineSetup":{"height":0,"shape":0,"cage":1,"couvette":2,"remeltingMachine":true}},{"id":62,"originalId":"7bf6403c-e96d-411f-a614-e43418f7fb5f","duration":7,"deadline":105,"compatibleMachines":["3","4","5","6","10","11","12","13"],"compatibleCages":[1],"compatibleCouvettes":[3],"machineSetup":{"height":1,"shape":1,"cage":1,"couvette":3,"remeltingMachine":false}},{"id":63,"originalId":"7e2ce704-3562-4b32-a3a1-43405ab12eca","duration":18,"deadline":-22,"compatibleMachines":["3","4","5","6","10","11","13"],"compatibleCages":[1,0],"compatibleCouvettes":[1],"machineSetup":{"height":1,"shape":1,"cage":1,"couvette":1,"remeltingMachine":false}},{"id":64,"originalId":"7e2ce704-3562-4b32-a3a1-43405ab12eca","duration":6,"deadline":-22,"compatibleMachines":["3","4","5","6","10","11","13"],"compatibleCages":[1,0],"compatibleCouvettes":[1],"machineSetup":{"height":1,"shape":1,"cage":1,"couvette":1,"remeltingMachine":false}},{"id":65,"originalId":"813f4605-c25a-4a94-9909-6c03f07acad1","duration":2,"deadline":158,"compatibleMachines":["3","4","5","6","10","11","13"],"compatibleCages":[1,0],"compatibleCouvettes":[0],"machineSetup":{"height":0,"shape":0,"cage":1,"couvette":0,"remeltingMachine":false}},{"id":66,"originalId":"847fd37e-4eec-4f0f-b4c0-90144a4bdb2b","duration":17,"deadline":9,"compatibleMachines":["3","4","5","6","10","11","13"],"compatibleCages":[1],"compatibleCouvettes":[3],"machineSetup":{"height":0,"shape":1,"cage":1,"couvette":3,"remeltingMachine":false}},{"id":67,"originalId":"895b8686-861d-47a3-9245-d4fe03d0d10f","duration":18,"deadline":131,"compatibleMachines":["4","11"],"compatibleCages":[1],"compatibleCouvettes":[4,5],"machineSetup":{"height":1,"shape":0,"cage":1,"couvette":5,"remeltingMachine":false}},{"id":68,"originalId":"895b8686-861d-47a3-9245-d4fe03d0d10f","duration":6,"deadline":131,"compatibleMachines":["4","11"],"compatibleCages":[1],"compatibleCouvettes":[4,5],"machineSetup":{"height":1,"shape":0,"cage":1,"couvette":5,"remeltingMachine":false}},{"id":69,"originalId":"8cbe0353-2151-4e5a-87a9-66399e4ad381","duration":13,"deadline":40,"compatibleMachines":["3","4","5","6","10","11","13"],"compatibleCages":[1,0],"compatibleCouvettes":[2,3],"machineSetup":{"height":1,"shape":1,"cage":1,"couvette":3,"remeltingMachine":false}},{"id":70,"originalId":"8e8ec3da-a38c-49c8-8bd0-3123a5a1ab2b","duration":8,"deadline":68,"compatibleMachines":["3","4","5","6","10","11","13"],"compatibleCages":[1,0],"compatibleCouvettes":[2,3],"machineSetup":{"height":1,"shape":1,"cage":1,"couvette":3,"remeltingMachine":false}},{"id":71,"originalId":"8f22f8fd-3c87-4c48-8246-62103bc7ceb8","duration":17,"deadline":-311,"compatibleMachines":["4","11"],"compatibleCages":[1],"compatibleCouvettes":[5],"machineSetup":{"height":1,"shape":1,"cage":1,"couvette":5,"remeltingMachine":false}},{"id":72,"originalId":"9452180d-b856-4c30-8096-438f9d105540","duration":5,"deadline":158,"compatibleMachines":["3","4","5","6","10","11","13"],"compatibleCages":[1],"compatibleCouvettes":[3],"machineSetup":{"height":0,"shape":1,"cage":1,"couvette":3,"remeltingMachine":false}},{"id":73,"originalId":"9b1f501f-bed8-40d7-a0f7-319d26fecc43","duration":3,"deadline":52,"compatibleMachines":["3","4","5","6","10","11","13"],"compatibleCages":[1],"compatibleCouvettes":[3],"machineSetup":{"height":0,"shape":1,"cage":1,"couvette":3,"remeltingMachine":false}},{"id":74,"originalId":"9c1b5569-e853-4c50-90d8-275dcecb81c8","duration":2,"deadline":-12,"compatibleMachines":["3","4","5","6","10","11","12","13"],"compatibleCages":[1],"compatibleCouvettes":[2,3],"machineSetup":{"height":0,"shape":1,"cage":1,"couvette":3,"remeltingMachine":false}},{"id":75,"originalId":"9d108a9f-f6d9-4a16-b0ef-3f0276793822","duration":18,"deadline":33,"compatibleMachines":["3","4","5","6","10","11","13"],"compatibleCages":[1,0],"compatibleCouvettes":[2,3],"machineSetup":{"height":1,"shape":1,"cage":1,"couvette":3,"remeltingMachine":false}},{"id":76,"originalId":"9d108a9f-f6d9-4a16-b0ef-3f0276793822","duration":16,"deadline":33,"compatibleMachines":["3","4","5","6","10","11","13"],"compatibleCages":[1,0],"compatibleCouvettes":[2,3],"machineSetup":{"height":1,"shape":1,"cage":1,"couvette":3,"remeltingMachine":false}},{"id":77,"originalId":"9e5ca3de-cf2f-4941-bcfe-427dc0c8114b","duration":11,"deadline":42,"compatibleMachines":["3","4","5","6","10","11","13"],"compatibleCages":[1],"compatibleCouvettes":[2,3],"machineSetup":{"height":0,"shape":0,"cage":1,"couvette":3,"remeltingMachine":false}},{"id":78,"originalId":"a54d3296-1425-44e6-8ed6-4bbce3e8d168","duration":2,"deadline":-49,"compatibleMachines":["3","4","5","6","10","11","13"],"compatibleCages":[1],"compatibleCouvettes":[0],"machineSetup":{"height":0,"shape":1,"cage":1,"couvette":0,"remeltingMachine":false}},{"id":79,"originalId":"a5cebb1a-33d9-487e-a2c6-c81a8145ff8e","duration":18,"deadline":21,"compatibleMachines":["4","11"],"compatibleCages":[1],"compatibleCouvettes":[5],"machineSetup":{"height":1,"shape":1,"cage":1,"couvette":5,"remeltingMachine":false}},{"id":80,"originalId":"a5cebb1a-33d9-487e-a2c6-c81a8145ff8e","duration":18,"deadline":21,"compatibleMachines":["4","11"],"compatibleCages":[1],"compatibleCouvettes":[5],"machineSetup":{"height":1,"shape":1,"cage":1,"couvette":5,"remeltingMachine":false}},{"id":81,"originalId":"a5cebb1a-33d9-487e-a2c6-c81a8145ff8e","duration":18,"deadline":21,"compatibleMachines":["4","11"],"compatibleCages":[1],"compatibleCouvettes":[5],"machineSetup":{"height":1,"shape":1,"cage":1,"couvette":5,"remeltingMachine":false}},{"id":82,"originalId":"a5cebb1a-33d9-487e-a2c6-c81a8145ff8e","duration":18,"deadline":21,"compatibleMachines":["4","11"],"compatibleCages":[1],"compatibleCouvettes":[5],"machineSetup":{"height":1,"shape":1,"cage":1,"couvette":5,"remeltingMachine":false}},{"id":83,"originalId":"a5cebb1a-33d9-487e-a2c6-c81a8145ff8e","duration":18,"deadline":21,"compatibleMachines":["4","11"],"compatibleCages":[1],"compatibleCouvettes":[5],"machineSetup":{"height":1,"shape":1,"cage":1,"couvette":5,"remeltingMachine":false}},{"id":84,"originalId":"a5cebb1a-33d9-487e-a2c6-c81a8145ff8e","duration":11,"deadline":21,"compatibleMachines":["4","11"],"compatibleCages":[1],"compatibleCouvettes":[5],"machineSetup":{"height":1,"shape":1,"cage":1,"couvette":5,"remeltingMachine":false}},{"id":85,"originalId":"aaf1bd74-47c1-44fd-89f3-12437f512df7","duration":7,"deadline":105,"compatibleMachines":["3","4","5","6","10","11","13"],"compatibleCages":[1,0],"compatibleCouvettes":[2,3],"machineSetup":{"height":1,"shape":1,"cage":1,"couvette":3,"remeltingMachine":false}},{"id":86,"originalId":"b533df5e-fe01-4d35-a84b-3afad991cd35","duration":18,"deadline":95,"compatibleMachines":["3","4","5","6","10","11","12","13"],"compatibleCages":[1,0],"compatibleCouvettes":[2,3],"machineSetup":{"height":1,"shape":1,"cage":1,"couvette":3,"remeltingMachine":false}},{"id":87,"originalId":"b63e9565-b807-45e1-9c7c-9dc5d3140807","duration":11,"deadline":-173,"compatibleMachines":["4","11"],"compatibleCages":[1],"compatibleCouvettes":[5],"machineSetup":{"height":1,"shape":1,"cage":1,"couvette":5,"remeltingMachine":false}},{"id":88,"originalId":"b7b52add-3d1d-43d3-a49b-152827c5cde2","duration":11,"deadline":30,"compatibleMachines":["3","4","5","6","10","11","12","13"],"compatibleCages":[1,0],"compatibleCouvettes":[3],"machineSetup":{"height":1,"shape":1,"cage":1,"couvette":3,"remeltingMachine":false}},{"id":89,"originalId":"b9f9f0ba-d593-4052-8364-3439dbfd71a8","duration":2,"deadline":120,"compatibleMachines":["4","11"],"compatibleCages":[1],"compatibleCouvettes":[4,5],"machineSetup":{"height":0,"shape":1,"cage":1,"couvette":5,"remeltingMachine":false}},{"id":90,"originalId":"bd8aa620-5bd5-403b-bb48-8ff4a246192d","duration":18,"deadline":14,"compatibleMachines":["3","4","5","6","10","11","13"],"compatibleCages":[1,0],"compatibleCouvettes":[2,3],"machineSetup":{"height":1,"shape":1,"cage":1,"couvette":3,"remeltingMachine":false}},{"id":91,"originalId":"bd8aa620-5bd5-403b-bb48-8ff4a246192d","duration":18,"deadline":14,"compatibleMachines":["3","4","5","6","10","11","13"],"compatibleCages":[1,0],"compatibleCouvettes":[2,3],"machineSetup":{"height":1,"shape":1,"cage":1,"couvette":3,"remeltingMachine":false}},{"id":92,"originalId":"bd8aa620-5bd5-403b-bb48-8ff4a246192d","duration":18,"deadline":14,"compatibleMachines":["3","4","5","6","10","11","13"],"compatibleCages":[1,0],"compatibleCouvettes":[2,3],"machineSetup":{"height":1,"shape":1,"cage":1,"couvette":3,"remeltingMachine":false}},{"id":93,"originalId":"bf012874-8dd0-4c4a-9228-c2e860fb619a","duration":15,"deadline":158,"compatibleMachines":["3","4","5","6","10","11","13"],"compatibleCages":[1,0],"compatibleCouvettes":[2,3],"machineSetup":{"height":1,"shape":1,"cage":1,"couvette":3,"remeltingMachine":false}},{"id":94,"originalId":"c303d427-f141-41d2-abb8-91f19b1375a1","duration":4,"deadline":189,"compatibleMachines":["3","6","12"],"compatibleCages":[0],"compatibleCouvettes":[3],"machineSetup":{"height":1,"shape":0,"cage":0,"couvette":3,"remeltingMachine":true}},{"id":95,"originalId":"c8f7a89a-5af2-4565-80af-7dcb156075a5","duration":2,"deadline":-23,"compatibleMachines":["3","6"],"compatibleCages":[1],"compatibleCouvettes":[0],"machineSetup":{"height":0,"shape":0,"cage":1,"couvette":0,"remeltingMachine":false}},{"id":96,"originalId":"cc19d4f5-cf88-4faf-9a06-cd6fe664043f","duration":9,"deadline":126,"compatibleMachines":["3","4","5","6","10","11","13"],"compatibleCages":[1,0],"compatibleCouvettes":[2,3],"machineSetup":{"height":1,"shape":1,"cage":1,"couvette":3,"remeltingMachine":false}},{"id":97,"originalId":"ce75deb2-3a69-46a7-aafd-bdc797b86e78","duration":2,"deadline":-77,"compatibleMachines":["4","11"],"compatibleCages":[1],"compatibleCouvettes":[3],"machineSetup":{"height":1,"shape":1,"cage":1,"couvette":3,"remeltingMachine":false}},{"id":98,"originalId":"cf4020bb-65d5-4c1b-b054-b6ec49cc1304","duration":2,"deadline":158,"compatibleMachines":["3","4","5","6","10","11","12","13"],"compatibleCages":[1,0],"compatibleCouvettes":[2,3],"machineSetup":{"height":0,"shape":1,"cage":1,"couvette":3,"remeltingMachine":false}},{"id":99,"originalId":"cfa4d9f8-2417-4910-ac7d-c63c55dd88ed","duration":18,"deadline":43,"compatibleMachines":["3","4","5","6","10","11","13"],"compatibleCages":[1,0],"compatibleCouvettes":[2,3],"machineSetup":{"height":1,"shape":1,"cage":1,"couvette":3,"remeltingMachine":false}},{"id":100,"originalId":"cfa4d9f8-2417-4910-ac7d-c63c55dd88ed","duration":18,"deadline":43,"compatibleMachines":["3","4","5","6","10","11","13"],"compatibleCages":[1,0],"compatibleCouvettes":[2,3],"machineSetup":{"height":1,"shape":1,"cage":1,"couvette":3,"remeltingMachine":false}},{"id":101,"originalId":"cfa4d9f8-2417-4910-ac7d-c63c55dd88ed","duration":18,"deadline":43,"compatibleMachines":["3","4","5","6","10","11","13"],"compatibleCages":[1,0],"compatibleCouvettes":[2,3],"machineSetup":{"height":1,"shape":1,"cage":1,"couvette":3,"remeltingMachine":false}},{"id":102,"originalId":"cfa4d9f8-2417-4910-ac7d-c63c55dd88ed","duration":17,"deadline":43,"compatibleMachines":["3","4","5","6","10","11","13"],"compatibleCages":[1,0],"compatibleCouvettes":[2,3],"machineSetup":{"height":1,"shape":1,"cage":1,"couvette":3,"remeltingMachine":false}},{"id":103,"originalId":"d2b10342-82ce-4156-a249-e1e2fc50ae8d","duration":2,"deadline":35,"compatibleMachines":["3","4","5","6","10","11","13"],"compatibleCages":[1],"compatibleCouvettes":[2,3],"machineSetup":{"height":0,"shape":1,"cage":1,"couvette":3,"remeltingMachine":false}},{"id":104,"originalId":"d4487124-e1c5-48d5-8e8f-2ecca93a310f","duration":2,"deadline":189,"compatibleMachines":["3","4","5","6","10","11","13"],"compatibleCages":[1],"compatibleCouvettes":[4,5],"machineSetup":{"height":1,"shape":1,"cage":1,"couvette":5,"remeltingMachine":false}},{"id":105,"originalId":"d495b722-7501-498c-8a98-11440efb72e7","duration":18,"deadline":74,"compatibleMachines":["3","4","5","6","10","11","13"],"compatibleCages":[1,0],"compatibleCouvettes":[2,3],"machineSetup":{"height":1,"shape":1,"cage":1,"couvette":3,"remeltingMachine":false}},{"id":106,"originalId":"d495b722-7501-498c-8a98-11440efb72e7","duration":18,"deadline":74,"compatibleMachines":["3","4","5","6","10","11","13"],"compatibleCages":[1,0],"compatibleCouvettes":[2,3],"machineSetup":{"height":1,"shape":1,"cage":1,"couvette":3,"remeltingMachine":false}},{"id":107,"originalId":"d495b722-7501-498c-8a98-11440efb72e7","duration":2,"deadline":74,"compatibleMachines":["3","4","5","6","10","11","13"],"compatibleCages":[1,0],"compatibleCouvettes":[2,3],"machineSetup":{"height":1,"shape":1,"cage":1,"couvette":3,"remeltingMachine":false}},{"id":108,"originalId":"dc114374-7511-4305-b075-98a3a3a0579b","duration":2,"deadline":145,"compatibleMachines":["3","4","5","6","10","11","12","13"],"compatibleCages":[1,0],"compatibleCouvettes":[1],"machineSetup":{"height":1,"shape":1,"cage":1,"couvette":1,"remeltingMachine":false}},{"id":109,"originalId":"dce4fddd-4b8e-44d7-bcbf-383d83c5ed98","duration":13,"deadline":142,"compatibleMachines":["3","4","5","6","10","11","13"],"compatibleCages":[1,0],"compatibleCouvettes":[2],"machineSetup":{"height":1,"shape":1,"cage":1,"couvette":2,"remeltingMachine":false}},{"id":110,"originalId":"e3fbc9d6-1402-483b-8c30-df72ed22a88e","duration":2,"deadline":196,"compatibleMachines":["3","4","5","6","10","11","13"],"compatibleCages":[1,0],"compatibleCouvettes":[3],"machineSetup":{"height":1,"shape":1,"cage":1,"couvette":3,"remeltingMachine":false}},{"id":111,"originalId":"e408b4fe-b9b8-4813-84d9-6b3c28394c73","duration":2,"deadline":-8,"compatibleMachines":["3","4","5","6","10","11","13"],"compatibleCages":[1],"compatibleCouvettes":[2],"machineSetup":{"height":0,"shape":1,"cage":1,"couvette":2,"remeltingMachine":false}},{"id":112,"originalId":"eb4c0a1f-e61d-4128-8bc1-4d6e8f3fce61","duration":2,"deadline":219,"compatibleMachines":["3","4","5","6","10","11","13"],"compatibleCages":[1,0],"compatibleCouvettes":[2,3],"machineSetup":{"height":1,"shape":1,"cage":1,"couvette":3,"remeltingMachine":false}},{"id":113,"originalId":"ec34d588-8f37-4627-9ae4-ce586efd5678","duration":2,"deadline":102,"compatibleMachines":["3","4","5","6","10","11","12","13"],"compatibleCages":[1,0],"compatibleCouvettes":[2,3],"machineSetup":{"height":0,"shape":1,"cage":1,"couvette":3,"remeltingMachine":false}},{"id":114,"originalId":"edc24954-1893-4806-99db-93e4a4b7f06f","duration":8,"deadline":158,"compatibleMachines":["4","11"],"compatibleCages":[1],"compatibleCouvettes":[3],"machineSetup":{"height":0,"shape":1,"cage":1,"couvette":3,"remeltingMachine":false}},{"id":115,"originalId":"ef44d3d1-715d-4c9d-a107-777bbad2a399","duration":2,"deadline":343,"compatibleMachines":["3","4","5","6","10","11","13"],"compatibleCages":[1,0],"compatibleCouvettes":[2,3],"machineSetup":{"height":1,"shape":1,"cage":1,"couvette":3,"remeltingMachine":false}},{"id":116,"originalId":"f2014b20-77e2-4841-afae-d5ec2080bee5","duration":18,"deadline":40,"compatibleMachines":["4","11"],"compatibleCages":[1],"compatibleCouvettes":[5],"machineSetup":{"height":1,"shape":1,"cage":1,"couvette":5,"remeltingMachine":false}},{"id":117,"originalId":"f2014b20-77e2-4841-afae-d5ec2080bee5","duration":2,"deadline":40,"compatibleMachines":["4","11"],"compatibleCages":[1],"compatibleCouvettes":[5],"machineSetup":{"height":1,"shape":1,"cage":1,"couvette":5,"remeltingMachine":false}},{"id":118,"originalId":"f45f8a02-5c7c-4499-88c4-8e2b858369e7","duration":2,"deadline":147,"compatibleMachines":["3","4","5","6","10","11","13"],"compatibleCages":[1,0],"compatibleCouvettes":[1,2],"machineSetup":{"height":1,"shape":1,"cage":1,"couvette":2,"remeltingMachine":false}},{"id":119,"originalId":"ff3adb1b-a663-4231-961f-1ab58d6512bb","duration":9,"deadline":98,"compatibleMachines":["3","4","5","6","10","11","13"],"compatibleCages":[1,0],"compatibleCouvettes":[1],"machineSetup":{"height":1,"shape":1,"cage":1,"couvette":1,"remeltingMachine":false}},{"id":120,"originalId":"ff632635-3548-4378-9556-e6aba8534af5","duration":2,"deadline":223,"compatibleMachines":["3","4","5","6","10","11","13"],"compatibleCages":[1,0],"compatibleCouvettes":[3],"machineSetup":{"height":1,"shape":1,"cage":1,"couvette":3,"remeltingMachine":false}}]